pyconfigurationmanager/__init__.py
pyconfigurationmanager/__main__.py
pyconfigurationmanager-0.1.2.dist-info/LICENSE
pyconfigurationmanager-0.1.2.dist-info/METADATA
pyconfigurationmanager-0.1.2.dist-info/WHEEL
pyconfigurationmanager-0.1.2.dist-info/top_level.txt
pyconfigurationmanager-0.1.2.dist-info/RECORD
