Metadata-Version: 2.1
Name: pyconfigurationmanager
Version: 0.1.2
Summary: The pyconfigurationmanager package provides a set of utilities for managing configuration settings in
Home-page: https://github.com/coldsofttech/pyconfigurationmanager
Author: coldsofttech
License: MIT
Keywords: configuration,configuration-management,config-manager
Classifier: Development Status :: 4 - Beta
Classifier: Intended Audience :: Developers
Classifier: Topic :: Software Development :: Libraries :: Python Modules
Classifier: Topic :: Utilities
Classifier: License :: OSI Approved :: MIT License
Classifier: Programming Language :: Python :: 3.10
Classifier: Programming Language :: Python :: 3.11
Classifier: Programming Language :: Python :: 3.12
License-File: LICENSE
Requires-Dist: pyloggermanager
